maler/__init__.py
maler/fastapi.py
maler/mjml.py
maler/mjml_tags.py
maler/renderer.py
maler/tags.py
maler-0.1.1.dist-info/WHEEL
maler-0.1.1.dist-info/METADATA
maler-0.1.1.dist-info/RECORD
