Metadata-Version: 2.3
Name: maler
Version: 0.1.1
Summary: Add your description here
Author: Mats E. Mollestad
Author-email: Mats E. Mollestad <mats@mollestad.no>
Requires-Dist: fastapi ; extra == 'fastapi'
Requires-Dist: pydantic>=2.0.0 ; extra == 'fastapi'
Requires-Dist: mrml ; extra == 'mjml'
Requires-Python: >=3.10
Provides-Extra: fastapi
Provides-Extra: mjml
